dirbpy.py
_dirbpy/URLBruteforcer.py
_dirbpy/WordDictonary.py
_dirbpy/__init__.py
_dirbpy/main.py
dirbpy-1.2.16.data/scripts/dirbpy
dirbpy-1.2.16.dist-info/LICENSE
dirbpy-1.2.16.dist-info/METADATA
dirbpy-1.2.16.dist-info/WHEEL
dirbpy-1.2.16.dist-info/top_level.txt
dirbpy-1.2.16.dist-info/RECORD
