Metadata-Version: 2.1
Name: dirbpy
Version: 1.2.16
Summary: This is the new version of dirb in python.
Home-page: https://github.com/marcolivierbouch/dirbpy
Author: Marc-Olivier Bouchard
Author-email: mo.bouchard1997@gmail.com
License: MIT license
Platform: unix
Platform: linux
Platform: osx
Classifier: Programming Language :: Python :: 3.7
Classifier: License :: OSI Approved :: MIT License
Classifier: Operating System :: OS Independent
Requires-Dist: argparse
Requires-Dist: requests
